romp/__init__.py
romp/__main__.py
romp/_core.py
romp/_matrix.py
romp/_version.py
romp/cli.py
romp/tests/__init__.py
romp/tests/print_sys_version.py
romp/tests/test_integration.py
romp-2021.11.dist-info/LICENSE
romp-2021.11.dist-info/METADATA
romp-2021.11.dist-info/WHEEL
romp-2021.11.dist-info/entry_points.txt
romp-2021.11.dist-info/top_level.txt
romp-2021.11.dist-info/RECORD
